LICENSE
README.md
pyproject.toml
setup.cfg
setup.py
tests/test_geometry_points.py
tests/test_geometry_se3.py
tests/test_geometry_vision.py
tests/test_probabilistic.py
tests/test_utils.py
torram/__init__.py
torram/preprocessing.py
torram/training.py
torram.egg-info/PKG-INFO
torram.egg-info/SOURCES.txt
torram.egg-info/dependency_links.txt
torram.egg-info/requires.txt
torram.egg-info/top_level.txt
torram/geometry/__init__.py
torram/geometry/points.py
torram/geometry/se3.py
torram/geometry/smpl.py
torram/geometry/vision.py
torram/probabilistic/__init__.py
torram/probabilistic/gmm.py
torram/probabilistic/kalman.py
torram/probabilistic/ops.py
torram/utils/__init__.py
torram/utils/config.py
torram/utils/dataset_utils.py
torram/utils/moderngl_utils.py
torram/utils/ops.py
torram/utils/rerun_utils.py
torram/utils/tum_dataset.py
torram/utils/visualization.py
torram/utils/wandb_utils.py