Metadata-Version: 2.1
Name: torram
Version: 1.7.7
Summary: Machine Learning essential tools for PyTorch.
Home-page: https://github.com/simon-schaefer/torram
Author: Simon Schaefer
Author-email: simon.k.schaefer@gmail.com
License: MIT
Platform: UNKNOWN
License-File: LICENSE
